ossTools/__init__.py
ossTools/_ossArchiveUtils.py
ossTools/_ossFile.py
ossTools/_ossIO.py
ossTools/_ossOpenCVUtils.py
ossTools/_ossPath.py
ossTools/_ossTensorBoardUtils.py
ossTools-0.1.16.dist-info/METADATA
ossTools-0.1.16.dist-info/WHEEL
ossTools-0.1.16.dist-info/top_level.txt
ossTools-0.1.16.dist-info/RECORD
